baroness/__init__.py
baroness/cache.py
baroness/cli.py
baroness/search.py
baroness/utils.py
baroness-1.3.0.dist-info/METADATA
baroness-1.3.0.dist-info/WHEEL
baroness-1.3.0.dist-info/entry_points.txt
baroness-1.3.0.dist-info/top_level.txt
baroness-1.3.0.dist-info/RECORD
