Metadata-Version: 2.1
Name: baroness
Version: 1.3.0
Summary: Toolkit for easy searching and manipulation of python source code using redbaron.
Home-page: https://github.com/smirl/baroness
Author: Alex Williams
Author-email: UNKNOWN
License: UNKNOWN
Platform: UNKNOWN
Requires-Dist: redbaron (>=0.6.3)
Requires-Dist: Pygments (>=2.2.0)
Requires-Dist: future (>=0.16.0)
Requires-Dist: futures (>=3.2.0); python_version < "3.2"
